{"version":3,"kind":"Article","sha256":"5891be93eaaed7bf3d429e0d7ccb3706c63abb65980539d5a92b18eddf61e43f","slug":"pages.m01-welcome","location":"/pages/002-m01-welcome.md","dependencies":[],"frontmatter":{"title":"Welcome!","content_includes_title":false,"authors":[{"nameParsed":{"literal":"Shawn Wiggins","given":"Shawn","family":"Wiggins"},"name":"Shawn Wiggins","affiliations":["City College of San Francisco"],"id":"contributors-myst-generated-uid-0"}],"license":{"content":{"id":"CC-BY-4.0","url":"https://creativecommons.org/licenses/by/4.0/","name":"Creative Commons Attribution 4.0 International","free":true,"CC":true}},"affiliations":[{"id":"City College of San Francisco","name":"City College of San Francisco"}],"numbering":{"title":{"offset":1}},"exports":[{"format":"md","filename":"002-m01-welcome.md","url":"/textbook/build/002-m01-welcome-20d6a886b35c0cb9cb66f3ba5571c2da.md"}]},"mdast":{"type":"root","children":[{"type":"block","children":[{"type":"paragraph","position":{"start":{"line":3,"column":1},"end":{"line":3,"column":1}},"children":[{"type":"emphasis","position":{"start":{"line":3,"column":1},"end":{"line":3,"column":1}},"children":[{"type":"text","value":"Welcome to Probability and Statistics!","position":{"start":{"line":3,"column":1},"end":{"line":3,"column":1}},"key":"bBfHRnQ5Yf"}],"key":"XIajE8KMhG"}],"key":"qvLAFvh9Uo"},{"type":"paragraph","position":{"start":{"line":5,"column":1},"end":{"line":5,"column":1}},"children":[{"type":"text","value":"We begin with a short section to prepare you for learning online. For some of you, this material may be part of a hybrid learning experience in which you also meet face-to-face with an instructor. Some of you may be taking this course solely online, with a lot, a little, or no interaction with an instructor. We discuss learning strategies for these different types of learning environments and give you some pointers for using this material to support your learning.","position":{"start":{"line":5,"column":1},"end":{"line":5,"column":1}},"key":"kZOeRie0ZA"}],"key":"MbJtcsaT7g"},{"type":"paragraph","position":{"start":{"line":7,"column":1},"end":{"line":7,"column":1}},"children":[{"type":"text","value":"We then discuss what statistics is all about—the “Big Picture” of statistics—and look at how the four steps in the Big Picture connect to the modules in the Probability and Statistics course.","position":{"start":{"line":7,"column":1},"end":{"line":7,"column":1}},"key":"mhBh8jeKT2"}],"key":"NUFeePmp3l"}],"key":"UboiDerk8S"}],"key":"nLPtvADw6S"},"references":{"cite":{"order":[],"data":{}}},"footer":{"navigation":{"prev":{"title":"Introduction to Statistics","url":"/","group":"Introduction to Statistics"},"next":{"title":"Pre-course Survey","url":"/pages/m01-pre-course-survey","group":"Unit 1: Introduction"}}},"domain":"http://localhost:3002"}